<?xml version="1.0" encoding="utf-8"?>

<odoo>
    <data>
        <record id="record_rule_purchase_order" model="ir.rule">
            <field name="name">Purchase Order Record Rule</field>
            <field name="model_id" ref="purchase.model_purchase_order"/>
            <field name="domain_force">[('create_uid', '=', user.id)]</field>
            <field name="groups" eval="[(4, ref('non_procurement_user'))]"/>
            <field name="perm_read" eval="True"/>
            <field name="perm_write" eval="True"/>
            <field name="perm_create" eval="True"/>
            <field name="perm_unlink" eval="True"/>
        </record>
    </data>
</odoo>